{
  "video_id": "5f0bba235170",
  "video_path": "C:\\Users\\bperr\\Desktop\\frame-truth\\frametruth_training\\data\\raw_videos\\5f0bba235170.mp4",
  "total_frames": 192,
  "fps": 24.0,
  "duration": 8.0,
  "original_resolution": [
    720,
    1280
  ],
  "processed_resolution": [
    256,
    256
  ],
  "frames_requested": 16,
  "frames_extracted": 16,
  "frames": [
    {
      "frame_index": 0,
      "original_frame_number": 0,
      "timestamp": 0.0,
      "filename": "frame_0000.jpg",
      "path": "C:\\Users\\bperr\\Desktop\\frame-truth\\frametruth_training\\data\\frames\\5f0bba235170\\frame_0000.jpg"
    },
    {
      "frame_index": 1,
      "original_frame_number": 12,
      "timestamp": 0.5,
      "filename": "frame_0001.jpg",
      "path": "C:\\Users\\bperr\\Desktop\\frame-truth\\frametruth_training\\data\\frames\\5f0bba235170\\frame_0001.jpg"
    },
    {
      "frame_index": 2,
      "original_frame_number": 24,
      "timestamp": 1.0,
      "filename": "frame_0002.jpg",
      "path": "C:\\Users\\bperr\\Desktop\\frame-truth\\frametruth_training\\data\\frames\\5f0bba235170\\frame_0002.jpg"
    },
    {
      "frame_index": 3,
      "original_frame_number": 36,
      "timestamp": 1.5,
      "filename": "frame_0003.jpg",
      "path": "C:\\Users\\bperr\\Desktop\\frame-truth\\frametruth_training\\data\\frames\\5f0bba235170\\frame_0003.jpg"
    },
    {
      "frame_index": 4,
      "original_frame_number": 48,
      "timestamp": 2.0,
      "filename": "frame_0004.jpg",
      "path": "C:\\Users\\bperr\\Desktop\\frame-truth\\frametruth_training\\data\\frames\\5f0bba235170\\frame_0004.jpg"
    },
    {
      "frame_index": 5,
      "original_frame_number": 60,
      "timestamp": 2.5,
      "filename": "frame_0005.jpg",
      "path": "C:\\Users\\bperr\\Desktop\\frame-truth\\frametruth_training\\data\\frames\\5f0bba235170\\frame_0005.jpg"
    },
    {
      "frame_index": 6,
      "original_frame_number": 72,
      "timestamp": 3.0,
      "filename": "frame_0006.jpg",
      "path": "C:\\Users\\bperr\\Desktop\\frame-truth\\frametruth_training\\data\\frames\\5f0bba235170\\frame_0006.jpg"
    },
    {
      "frame_index": 7,
      "original_frame_number": 84,
      "timestamp": 3.5,
      "filename": "frame_0007.jpg",
      "path": "C:\\Users\\bperr\\Desktop\\frame-truth\\frametruth_training\\data\\frames\\5f0bba235170\\frame_0007.jpg"
    },
    {
      "frame_index": 8,
      "original_frame_number": 96,
      "timestamp": 4.0,
      "filename": "frame_0008.jpg",
      "path": "C:\\Users\\bperr\\Desktop\\frame-truth\\frametruth_training\\data\\frames\\5f0bba235170\\frame_0008.jpg"
    },
    {
      "frame_index": 9,
      "original_frame_number": 108,
      "timestamp": 4.5,
      "filename": "frame_0009.jpg",
      "path": "C:\\Users\\bperr\\Desktop\\frame-truth\\frametruth_training\\data\\frames\\5f0bba235170\\frame_0009.jpg"
    },
    {
      "frame_index": 10,
      "original_frame_number": 120,
      "timestamp": 5.0,
      "filename": "frame_0010.jpg",
      "path": "C:\\Users\\bperr\\Desktop\\frame-truth\\frametruth_training\\data\\frames\\5f0bba235170\\frame_0010.jpg"
    },
    {
      "frame_index": 11,
      "original_frame_number": 132,
      "timestamp": 5.5,
      "filename": "frame_0011.jpg",
      "path": "C:\\Users\\bperr\\Desktop\\frame-truth\\frametruth_training\\data\\frames\\5f0bba235170\\frame_0011.jpg"
    },
    {
      "frame_index": 12,
      "original_frame_number": 144,
      "timestamp": 6.0,
      "filename": "frame_0012.jpg",
      "path": "C:\\Users\\bperr\\Desktop\\frame-truth\\frametruth_training\\data\\frames\\5f0bba235170\\frame_0012.jpg"
    },
    {
      "frame_index": 13,
      "original_frame_number": 156,
      "timestamp": 6.5,
      "filename": "frame_0013.jpg",
      "path": "C:\\Users\\bperr\\Desktop\\frame-truth\\frametruth_training\\data\\frames\\5f0bba235170\\frame_0013.jpg"
    },
    {
      "frame_index": 14,
      "original_frame_number": 168,
      "timestamp": 7.0,
      "filename": "frame_0014.jpg",
      "path": "C:\\Users\\bperr\\Desktop\\frame-truth\\frametruth_training\\data\\frames\\5f0bba235170\\frame_0014.jpg"
    },
    {
      "frame_index": 15,
      "original_frame_number": 180,
      "timestamp": 7.5,
      "filename": "frame_0015.jpg",
      "path": "C:\\Users\\bperr\\Desktop\\frame-truth\\frametruth_training\\data\\frames\\5f0bba235170\\frame_0015.jpg"
    }
  ]
}